{
  "title": "Tylen St Hilaire ‧ User Experience Architect & Designer",
  "url": "https://tylensthilaire.com/",
  "description": "The work of Tylen St Hilaire, a UX architect & designer blending art, human factors and digital technology into meaningful experiences.",
  "feed": {
    "subtitle": "The work of Tylen St Hilaire, blending art, human factors and technology into meaningful experiences.",
    "filename": "feed.xml",
    "path": "/feed/feed.xml",
    "id": "https://tylensthilaire.com/"
  },
  "jsonfeed": {
    "path": "/feed/feed.json",
    "url": "https://tylensthilaire.com/feed/feed.json"
  },
  "author": {
    "name": "Tylen St Hilaire",
    "email": "hello@tylensthilaire.com",
    "url": "https://tylensthilaire.com/about-me/"
  }
}
